{"copyright": "Copyright (c) 2013 The New York Times Company.  All Rights Reserved.", "status": "OK", "response": {"docs": [{"blog": [], "section_name": null, "print_page": "4", "headline": {"kicker": "1", "main": "City Mortality."}, "type_of_material": "Article", "word_count": 750, "web_url": "http://query.nytimes.com/gst/abstract.html?res=9902E2DE103AE334BC4153DFB766838F649FDE", "_id": "4fbfd6d245c1498b0d01abb8", "multimedia": [], "slideshow_credits": null, "lead_paragraph": "Four hundred and eighty-one persons were buried in this City last week. The number is one less than the week preceding, and about the expected average for the season. Consumption killed 63 of them. Of course by this word \"consumption\" is meant almost all sorts of diseases upon which a cough attends, which the physician fails to cure.", "abstract": null, "snippet": "Four hundred and eighty-one persons were buried in this City last week. The number is one less than the week preceding, and about the expected average for the season. Consumption killed 63 of them. Of course by this word \"consumption\" is meant almost...", "keywords": [], "byline": null, "document_type": "article", "pub_date": "1854-01-09T00:03:58Z", "news_desk": null, "source": "The New York Times", "subsection_name": null}], "meta": {"offset": 10, "time": 66, "hits": 11}}}