{"status": "OK", "response": {"docs": [{"type_of_material": "Summary", "blog": [], "news_desk": "Metropolitan Desk", "lead_paragraph": "INTERNATIONAL A3-17 China's favorable trading status should be extended for another year, President Bush said, in a move that reopened a conflict with Congress over relations with China and even surprised his staff. Page A1 Senate asks Bush to back loan guarantees for Soviets D1", "headline": {"main": "NEWS SUMMARY"}, "abstract": null, "print_page": "2", "word_count": 1143, "_id": "4fd19e168eb7c8105d6b07ae", "snippet": "INTERNATIONAL A3-17    China's favorable trading status should be extended for another year, President Bush said, in a move that reopened a conflict with Congress over relations with China and even surprised his staff. Page A1    Senate asks Bush to...", "source": "The New York Times", "slideshow_credits": null, "web_url": "http://www.nytimes.com/1991/05/16/nyregion/news-summary-893491.html", "multimedia": [], "subsection_name": null, "keywords": [{"name": "subject", "value": "NO INDEX TERMS"}], "byline": null, "document_type": "article", "pub_date": "1991-05-16T00:00:00Z", "section_name": "New York and Region"}], "meta": {"hits": 1, "offset": 0, "time": 145}}, "copyright": "Copyright (c) 2013 The New York Times Company.  All Rights Reserved."}