{"status": "OK", "response": {"docs": [{"type_of_material": "Letter", "blog": [], "news_desk": null, "lead_paragraph": null, "headline": {"main": "Letters to The Times"}, "abstract": null, "print_page": "30", "word_count": 2163, "_id": "4fc41c8145c1498b0d91ef47", "snippet": null, "source": "The New York Times", "slideshow_credits": null, "web_url": "http://query.nytimes.com/gst/abstract.html?res=9400E4DE1F3DE53BBC4053DFB5668389679EDE", "multimedia": [], "subsection_name": null, "keywords": [{"name": "persons", "value": "ROOSEVELT, FRANKLIN DELANO"}, {"name": "persons", "value": "FARADAY, MICHAEL"}, {"name": "glocations", "value": "UNITED STATES"}, {"name": "glocations", "value": "NEW YORK CITY"}, {"name": "glocations", "value": "VIETNAM"}, {"name": "glocations", "value": "BRAZIL"}, {"name": "subject", "value": "ASTRONAUTICS"}, {"name": "subject", "value": "US PROJECTS (GENERAL)"}, {"name": "subject", "value": "ASTRONAUTICS"}, {"name": "subject", "value": "FRENCH PROJECTS (GENERAL)"}, {"name": "subject", "value": "MEDICINE AND HEALTH"}, {"name": "subject", "value": "TEACHERS AND SCHOOL SYSTEM EMPLOYES"}], "byline": null, "document_type": "article", "pub_date": "1962-03-08T00:00:00Z", "section_name": null}], "meta": {"hits": 1, "offset": 0, "time": 44}}, "copyright": "Copyright (c) 2013 The New York Times Company.  All Rights Reserved."}