{"status": "OK", "response": {"docs": [{"type_of_material": "Article", "blog": [], "news_desk": null, "lead_paragraph": "THE Montross Galleries are holding a special exhibition of contemporary art which includes one new name, that of J.B. Flanagan, who works in wood and wax with, for the most part, religious themes. The twisted figures of his carved wooden panels are elongated to a Grecoesque tenuity.", "headline": {"main": "ART THE HEIGHT OF EXHIBITION SEASON -- HOME AND FOREIGN NOTES"}, "abstract": "Shore, Henrietta, paintings, Ehrich Gal", "print_page": "X7", "word_count": 3289, "_id": "4fc08df045c1498b0d36469d", "snippet": "THE Montross Galleries are holding a special exhibition of contemporary art which includes one new name, that of J.B. Flanagan, who works in wood and wax with, for the most part, religious themes. The twisted figures of his carved wooden panels are...", "source": "The New York Times", "slideshow_credits": null, "web_url": "http://query.nytimes.com/gst/abstract.html?res=9E06E4DE1630E333A2575BC2A9679C946295D6CF", "multimedia": [], "subsection_name": null, "keywords": [{"name": "subject", "value": "ART"}, {"name": "subject", "value": "EXHIBITIONS"}, {"name": "subject", "value": "ART"}, {"name": "subject", "value": "EXHIBITIONS"}, {"name": "subject", "value": "ART"}, {"name": "subject", "value": "EXHIBITIONS"}, {"name": "subject", "value": "ART"}, {"name": "subject", "value": "EXHIBITIONS"}, {"name": "subject", "value": "ART"}, {"name": "subject", "value": "EXHIBITIONS"}, {"name": "subject", "value": "ART"}, {"name": "subject", "value": "EXHIBITIONS"}, {"name": "subject", "value": "ART"}, {"name": "subject", "value": "EXHIBITIONS"}, {"name": "subject", "value": "ART"}, {"name": "subject", "value": "EXHIBITIONS"}], "byline": null, "document_type": "article", "pub_date": "1923-01-28T00:00:00Z", "section_name": null}], "meta": {"hits": 1, "offset": 0, "time": 33}}, "copyright": "Copyright (c) 2013 The New York Times Company.  All Rights Reserved."}