{"status": "OK", "response": {"docs": [{"type_of_material": "Blog", "blog": [], "news_desk": null, "lead_paragraph": "Can women with herpes have a natural birth? Can the herpes simplex virus (HSV) type 1 or 2 that causes genital herpes be dangerous for the newborn child? Those are among the questions posed by readers of the Consults blog in \"5 Things to Know About Herpes.\"", "headline": {"main": "Is Herpes a Danger During Pregnancy?", "kicker": "Consults"}, "abstract": "Genital herpes may be most dangerous late in pregnancy, says Dr. Peter Leone.", "print_page": null, "word_count": 292, "_id": "4fd39a8d8eb7c8105d8d7d96", "snippet": "Genital herpes may be most dangerous late in pregnancy, says Dr. Peter Leone.", "source": "The New York Times", "slideshow_credits": null, "web_url": "http://consults.blogs.nytimes.com/2010/05/31/is-herpes-a-danger-during-pregnancy/", "multimedia": [], "subsection_name": null, "keywords": [{"value": "News", "name": "type_of_material", "rank": "1"}], "byline": {"organization": "THE NEW YORK TIMES", "original": "By THE NEW YORK TIMES", "person": []}, "document_type": "blogpost", "pub_date": "2010-05-31T11:02:59Z", "section_name": "Health"}, {"type_of_material": "Letter", "blog": [], "news_desk": "Letters", "lead_paragraph": "Readers respond to a recent column.", "headline": {"main": "A Nun\u2019s Excommunication Over an Abortion Decision", "sub": "(4 Letters)", "print_headline": "A Nun\u2019s Excommunication Over an Abortion Decision", "content_kicker": "Letters"}, "abstract": null, "print_page": "", "word_count": "809", "_id": "5446e82079881004ee627cb4", "snippet": "Readers respond to a recent column.", "source": "The New York Times", "slideshow_credits": null, "web_url": "http://www.nytimes.com/2010/05/30/opinion/lweb30kristof.html", "multimedia": [], "subsection_name": null, "keywords": [{"rank": "1", "is_major": "N", "value": "Roman Catholic Church", "name": "organizations"}, {"rank": "2", "is_major": "N", "value": "Nuns", "name": "subject"}, {"rank": "3", "is_major": "N", "value": "Excommunication", "name": "subject"}, {"rank": "4", "is_major": "N", "value": "Abortion", "name": "subject"}], "byline": [], "document_type": "article", "pub_date": "2010-05-30T00:00:00Z", "section_name": "Opinion"}], "meta": {"hits": 2, "offset": 0, "time": 33}}, "copyright": "Copyright (c) 2013 The New York Times Company.  All Rights Reserved."}