{"status": "OK", "response": {"docs": [{"type_of_material": "Correction", "blog": [], "news_desk": "Metropolitan Desk", "lead_paragraph": "An article on Saturday about an appearance by Hillary Rodham Clinton before a meeting of doctors in Las Vegas, Nev., misidentified an obstetrician who told her that trial lawyers as well as doctors should be willing to sacrifice for health care reform. He was Dr. Allan Boruszak, not Dr. William Bossak.", "headline": {"main": "Corrections"}, "abstract": null, "print_page": "2", "word_count": 51, "_id": "4fd1bfa28eb7c8105d6eddeb", "snippet": "An article on Saturday about an appearance by Hillary Rodham Clinton before a meeting of doctors in Las Vegas, Nev., misidentified an obstetrician who told her that trial lawyers as well as doctors should be willing to sacrifice for health care...", "source": "The New York Times", "slideshow_credits": null, "web_url": "http://www.nytimes.com/1994/02/02/nyregion/c-corrections-057827.html", "multimedia": [], "subsection_name": null, "keywords": [{"name": "persons", "value": "CLINTON, HILLARY RODHAM"}, {"name": "subject", "value": "REFORM AND REORGANIZATION"}, {"name": "subject", "value": "HEALTH INSURANCE"}, {"name": "subject", "value": "MEDICINE AND HEALTH"}, {"name": "subject", "value": "CORRECTION STORIES"}], "byline": null, "document_type": "article", "pub_date": "1994-02-02T00:00:00Z", "section_name": "Corrections; New York and Region"}], "meta": {"hits": 41, "offset": 40, "time": 39}}, "copyright": "Copyright (c) 2013 The New York Times Company.  All Rights Reserved."}