{"response": {"meta": {"time": 25, "hits": 1, "offset": 0}, "docs": [{"news_desk": "Living Desk", "document_type": "article", "_id": "4fd12f728eb7c8105d5fc0e0", "headline": {"main": "MALNOURISHED CHILDREN"}, "pub_date": "1983-11-02T00:00:00Z", "slideshow_credits": null, "source": "The New York Times", "byline": {"original": "AP", "organization": "AP", "person": []}, "abstract": null, "web_url": "http://www.nytimes.com/1983/11/02/garden/malnourished-children.html", "section_name": "Home and Garden; Health", "lead_paragraph": "Some 10,000 to 17,500 poor children younger than school age in Massachusetts may be chronically malnourished, according to a health study made public Monday. The State Department of Public Health's 1983 Massachusetts Nutrition Survey represents a study of 1,429 low-income children aged 6 months to 6 years.", "snippet": "Some 10,000 to 17,500 poor children younger than school age in Massachusetts may be chronically malnourished, according to a health study made public Monday.   The State Department of Public Health's 1983 Massachusetts Nutrition Survey represents a...", "blog": [], "keywords": [{"value": "UNITED STATES (1983 PART 1)", "name": "glocations"}, {"value": "MASSACHUSETTS", "name": "glocations"}, {"value": "DIET AND NUTRITION", "name": "subject"}, {"value": "FOOD AND GROCERY TRADE", "name": "subject"}, {"value": "CHILDREN AND YOUTH", "name": "subject"}], "print_page": "14", "type_of_material": "News", "word_count": 244, "subsection_name": null, "multimedia": []}]}, "status": "OK", "copyright": "Copyright (c) 2013 The New York Times Company.  All Rights Reserved."}