{"status": "OK", "response": {"docs": [{"type_of_material": "Article", "blog": [], "news_desk": null, "lead_paragraph": "FOCAL EXHIBIT: Without production there obviously would not be much distribution; and without distribution, consumption would be limited. The lesson of interdependence is plain, and this focal exhibit, in the Consumers Building, was designed by Egmont Arens to drive home that lesson.", "headline": {"main": "THE EXHIBITS: AN AMAZING ARRAY; Production and Distribution"}, "abstract": "City; stills shown at N Y World's Fair; illus", "print_page": "128", "word_count": 16738, "_id": "4fc2055445c1498b0d5a325a", "snippet": "FOCAL EXHIBIT: Without production there obviously would not be much distribution; and without distribution, consumption would be limited. The lesson of interdependence is plain, and this focal exhibit, in the Consumers Building, was designed by...", "source": "The New York Times", "slideshow_credits": null, "web_url": "http://query.nytimes.com/gst/abstract.html?res=9A0DE5DA113EE33ABC4850DFB2668382629EDE", "multimedia": [], "subsection_name": null, "keywords": [{"name": "creative_works", "value": "CITY"}, {"name": "persons", "value": "GEORGE VI, KING OF GT BRIT AND IRELAND"}, {"name": "glocations", "value": "GERMANY"}, {"name": "glocations", "value": "GERMANY"}, {"name": "glocations", "value": "CHURCHILL DOWNS"}, {"name": "glocations", "value": "CHINA"}, {"name": "organizations", "value": "PANAMA RR SS LINE"}, {"name": "subject", "value": "FOREIGN RELATIONS"}, {"name": "subject", "value": "FOREIGN RELATIONS"}, {"name": "subject", "value": "ANIMALS"}, {"name": "subject", "value": "HORSES"}, {"name": "subject", "value": "RACES"}, {"name": "subject", "value": "FISH AND FISHING"}, {"name": "subject", "value": "GENERAL"}, {"name": "subject", "value": "FURNITURE"}, {"name": "subject", "value": "MOVING PICTURES"}, {"name": "subject", "value": "REVIEWS AND NOTES"}], "byline": null, "document_type": "article", "pub_date": "1939-04-30T00:00:00Z", "section_name": null}], "meta": {"hits": 1, "offset": 0, "time": 50}}, "copyright": "Copyright (c) 2013 The New York Times Company.  All Rights Reserved."}